pyaddroute/__main__.py
pyaddroute/main.py
pyaddroute-0.1.0.dist-info/METADATA
pyaddroute-0.1.0.dist-info/WHEEL
pyaddroute-0.1.0.dist-info/entry_points.txt
pyaddroute-0.1.0.dist-info/top_level.txt
pyaddroute-0.1.0.dist-info/RECORD
