Metadata-Version: 2.4
Name: pyaddroute
Version: 0.1.0
Summary: A tool for managing network routes on Windows systems
Author-email: fxyzbtc <fxyzbtc@users.noreply.github.com>
License: MIT
Project-URL: Homepage, https://github.com/fxyzbtc/pyaddroute
Project-URL: Repository, https://github.com/fxyzbtc/pyaddroute
Project-URL: Bug Tracker, https://github.com/fxyzbtc/pyaddroute/issues
Project-URL: Documentation, https://github.com/fxyzbtc/pyaddroute#readme
Keywords: network,routing,windows,ipv4
Classifier: Development Status :: 4 - Beta
Classifier: Environment :: Console
Classifier: Intended Audience :: System Administrators
Classifier: License :: OSI Approved :: MIT License
Classifier: Operating System :: Microsoft :: Windows
Classifier: Programming Language :: Python :: 3.8
Classifier: Programming Language :: Python :: 3.9
Classifier: Programming Language :: Python :: 3.10
Classifier: Programming Language :: Python :: 3.11
Classifier: Programming Language :: Python :: 3.12
Classifier: Topic :: System :: Networking
Classifier: Topic :: System :: Systems Administration
Requires-Python: >=3.8
Requires-Dist: freesimplegui>=4.60.0
Requires-Dist: loguru>=0.7.0
